auto_instr/__init__.py
auto_instr/adapter.py
auto_instr/agilent34405dmm.py
auto_instr/agilent3631a.py
auto_instr/datalog.py
auto_instr/dpo7104.py
auto_instr/hpmm3458A.py
auto_instr/infiniium80000.py
auto_instr/infiniium90804A.py
auto_instr/keithley2000.py
auto_instr/keithley2400.py
auto_instr/keithley2600.py
auto_instr/keysight33600afg.py
auto_instr/lecroysda8131z.py
auto_instr/mso54.py
auto_instr/psw_800.py
auto_instr/tektronixafg3102.py
auto_instr/tempforce.py
auto_instr/tempforce_t2500.py
auto_instr-0.9.5.dist-info/DESCRIPTION.rst
auto_instr-0.9.5.dist-info/METADATA
auto_instr-0.9.5.dist-info/RECORD
auto_instr-0.9.5.dist-info/WHEEL
auto_instr-0.9.5.dist-info/metadata.json
auto_instr-0.9.5.dist-info/top_level.txt
