Metadata-Version: 2.0
Name: auto-instr
Version: 0.9.5
Summary: Library for automating scientific instruments.
Home-page: https://github.com/arvind0790/auto_instr
Author: Arvind Kumar
Author-email: vind0790@gmail.com
License: MIT License
Keywords: measure instrument experiment control automate bench smu power supply oscilloscope thermonic function generator
Platform: UNKNOWN
Classifier: Development Status :: 4 - Beta
Classifier: Intended Audience :: Science/Research
Classifier: License :: OSI Approved :: MIT License
Classifier: Operating System :: MacOS
Classifier: Operating System :: Microsoft :: Windows
Classifier: Operating System :: POSIX
Classifier: Operating System :: Unix
Classifier: Programming Language :: Python :: 3 :: Only
Classifier: Topic :: Scientific/Engineering
License-File: LICENSE
